python_on_whales/__init__.py
python_on_whales/client_config.py
python_on_whales/command_line_entrypoint.py
python_on_whales/docker_client.py
python_on_whales/exceptions.py
python_on_whales/py.typed
python_on_whales/test_utils.py
python_on_whales/utils.py
python_on_whales/components/__init__.py
python_on_whales/components/buildx/__init__.py
python_on_whales/components/buildx/cli_wrapper.py
python_on_whales/components/buildx/models.py
python_on_whales/components/buildx/imagetools/__init__.py
python_on_whales/components/buildx/imagetools/cli_wrapper.py
python_on_whales/components/buildx/imagetools/models.py
python_on_whales/components/compose/__init__.py
python_on_whales/components/compose/cli_wrapper.py
python_on_whales/components/compose/models.py
python_on_whales/components/config/__init__.py
python_on_whales/components/config/cli_wrapper.py
python_on_whales/components/config/models.py
python_on_whales/components/container/__init__.py
python_on_whales/components/container/cli_wrapper.py
python_on_whales/components/container/models.py
python_on_whales/components/context/__init__.py
python_on_whales/components/context/cli_wrapper.py
python_on_whales/components/context/models.py
python_on_whales/components/image/__init__.py
python_on_whales/components/image/cli_wrapper.py
python_on_whales/components/image/models.py
python_on_whales/components/manifest/__init__.py
python_on_whales/components/manifest/cli_wrapper.py
python_on_whales/components/manifest/models.py
python_on_whales/components/network/__init__.py
python_on_whales/components/network/cli_wrapper.py
python_on_whales/components/network/models.py
python_on_whales/components/node/__init__.py
python_on_whales/components/node/cli_wrapper.py
python_on_whales/components/node/models.py
python_on_whales/components/plugin/__init__.py
python_on_whales/components/plugin/cli_wrapper.py
python_on_whales/components/plugin/models.py
python_on_whales/components/pod/__init__.py
python_on_whales/components/pod/cli_wrapper.py
python_on_whales-0.80.0.dist-info/METADATA
python_on_whales-0.80.0.dist-info/WHEEL
python_on_whales-0.80.0.dist-info/entry_points.txt
python_on_whales-0.80.0.dist-info/top_level.txt
python_on_whales-0.80.0.dist-info/RECORD
