Metadata-Version: 2.1
Name: python-on-whales
Version: 0.80.0
Summary: A Docker client for Python, designed to be fun and intuitive!
License: MIT License
Project-URL: Source, https://github.com/gabrieldemarmiesse/python-on-whales
Project-URL: Documentation, https://gabrieldemarmiesse.github.io/python-on-whales/
Project-URL: Bug Tracker, https://github.com/gabrieldemarmiesse/python-on-whales/issues
Requires-Python: <4,>=3.8
Requires-Dist: pydantic !=2.0.*,<3,>=2
Requires-Dist: typing-extensions
